wml_ai_model_managers/__init__.py
wml_ai_model_managers/text_model_manager_one/__init__.py
wml_ai_model_managers/text_model_manager_one/block.py
wml_ai_model_managers/text_model_manager_one/dataset.py
wml_ai_model_managers/text_model_manager_one/feedforward.py
wml_ai_model_managers/text_model_manager_one/head.py
wml_ai_model_managers/text_model_manager_one/model.py
wml_ai_model_managers/text_model_manager_one/model_manager.py
wml_ai_model_managers/text_model_manager_one/multi_head_attention.py
wml_ai_model_managers/text_model_manager_zero/__init__.py
wml_ai_model_managers/text_model_manager_zero/block.py
wml_ai_model_managers/text_model_manager_zero/feedforward.py
wml_ai_model_managers/text_model_manager_zero/head.py
wml_ai_model_managers/text_model_manager_zero/model.py
wml_ai_model_managers/text_model_manager_zero/model_manager.py
wml_ai_model_managers/text_model_manager_zero/multi_head_attention.py
wml_ai_model_managers/vision_model_manager_zero/__init__.py
wml_ai_model_managers/vision_model_manager_zero/block.py
wml_ai_model_managers/vision_model_manager_zero/feedforward.py
wml_ai_model_managers/vision_model_manager_zero/head.py
wml_ai_model_managers/vision_model_manager_zero/model.py
wml_ai_model_managers/vision_model_manager_zero/model_manager.py
wml_ai_model_managers/vision_model_manager_zero/multi_head_attention.py
wml_ai_model_managers/wml_utils/__init__.py
wml_ai_model_managers/wml_utils/common_utils.py
wml_ai_model_managers/wml_utils/error_utils.py
wml_ai_model_managers-1.1.1.dist-info/LICENSE
wml_ai_model_managers-1.1.1.dist-info/METADATA
wml_ai_model_managers-1.1.1.dist-info/WHEEL
wml_ai_model_managers-1.1.1.dist-info/top_level.txt
wml_ai_model_managers-1.1.1.dist-info/RECORD
