Metadata-Version: 2.1
Name: wml_ai_model_managers
Version: 1.1.1
Summary: A package for training and communicating with AI chatbots based on pytorch
Author-email: Windmillcode <dev@windmillcode.com>
Project-URL: Github, https://github.com/WindMillCode/python-libs/tree/main/wml_ai_model_managers-package
Classifier: Programming Language :: Python :: 3
Classifier: License :: OSI Approved :: MIT License
Classifier: Operating System :: OS Independent
Classifier: Programming Language :: Python :: 3
Classifier: Intended Audience :: Developers
Requires-Python: >=3.11
License-File: LICENSE
